pkg_genins/__init__.py
pkg_genins/generate_instruction.py
pkg_genins/utils.py
pkg_genins-0.0.3.dist-info/METADATA
pkg_genins-0.0.3.dist-info/WHEEL
pkg_genins-0.0.3.dist-info/top_level.txt
pkg_genins-0.0.3.dist-info/RECORD
