Metadata-Version: 2.4
Name: pkg_genins
Version: 0.0.3
Summary: 用于生成指令对的包
Author-email: Peiwen <pwshyu@gmail.com>
Project-URL: Homepage, https://github.com/peiwen-shyu/pkg
Classifier: Programming Language :: Python :: 3
Classifier: License :: OSI Approved :: MIT License
Classifier: Operating System :: OS Independent
Requires-Python: >=3.10
